hillcipher/__init__.py
hillcipher/hillcipher.py
hillcipher-0.0.4.dist-info/METADATA
hillcipher-0.0.4.dist-info/WHEEL
hillcipher-0.0.4.dist-info/top_level.txt
hillcipher-0.0.4.dist-info/RECORD
